pyxetabase/__init__.py
pyxetabase/commons.py
pyxetabase/exceptions.py
pyxetabase/opencga_client.py
pyxetabase/opencga_config.py
pyxetabase/rest_response.py
pyxetabase/retry.py
pyxetabase/rest_clients/__init__.py
pyxetabase/rest_clients/_parent_rest_clients.py
pyxetabase/rest_clients/admin_client.py
pyxetabase/rest_clients/alignment_client.py
pyxetabase/rest_clients/clinical_analysis_client.py
pyxetabase/rest_clients/cohort_client.py
pyxetabase/rest_clients/cvdb_client.py
pyxetabase/rest_clients/disease_panel_client.py
pyxetabase/rest_clients/family_client.py
pyxetabase/rest_clients/federation_client.py
pyxetabase/rest_clients/file_client.py
pyxetabase/rest_clients/ga4gh_client.py
pyxetabase/rest_clients/individual_client.py
pyxetabase/rest_clients/job_client.py
pyxetabase/rest_clients/meta_client.py
pyxetabase/rest_clients/organization_client.py
pyxetabase/rest_clients/project_client.py
pyxetabase/rest_clients/sample_client.py
pyxetabase/rest_clients/study_client.py
pyxetabase/rest_clients/user_client.py
pyxetabase/rest_clients/variant_client.py
pyxetabase/rest_clients/variant_operation_client.py
pyxetabase/rest_clients/workflow_client.py
pyxetabase-3.1.2.dist-info/licenses/LICENSE
pyxetabase-3.1.2.dist-info/METADATA
pyxetabase-3.1.2.dist-info/WHEEL
pyxetabase-3.1.2.dist-info/top_level.txt
pyxetabase-3.1.2.dist-info/RECORD
